common_tools/test_axi_include.v

// TB must be defined in testbench before including this file
// NUMBER_OF_TESTS must be defined in testbench before including this file

`define TEST_TASKS  `TB.test_tasks
`define TEST_PASSED `TEST_TASKS.test_passed
`define TEST_FAILED `TEST_TASKS.test_failed
`define TEST_COMPARE  `TEST_TASKS.compare_values
`define TEST_COMPLETE `TEST_TASKS.all_tests_completed

common_tools/dump.v
//                              -*- Mode: Verilog -*-
// Filename        : dump.v<common_tools>
// Description     : dump to waveform viewer
// Author          : Philip Tracton
// Created On      : Sat Mar 23 14:26:58 2019
// Last Modified By: Philip Tracton
// Last Modified On: Sat Mar 23 14:26:58 2019
// Update Count    : 0
// Status          : Unknown, Use with caution!

module dump (/*AUTOARG*/ ) ;
   //
   // Store results in waveform viewer format
   //
   initial
     begin
`ifdef NCVERILOG
	    $shm_open("dump.shm");
	    $shm_probe(tb_fifo, "MAC");
`else
	    $dumpfile("dump.vcd");
	    $dumpvars(0, `TB);
`endif
     end // initial begin

endmodule // dump

common_tools/test_tasks.v
//                              -*- Mode: Verilog -*-
// Filename        : test_tasks.v
// Description     : Tasks to help test the code
// Author          : Philip Tracton
// Created On      : Fri Dec  4 12:34:28 2015
// Last Modified By: Philip Tracton
// Last Modified On: Fri Dec  4 12:34:28 2015
// Update Count    : 0
// Status          : Unknown, Use with caution!


module test_tasks (/*AUTOARG*/ ) ;

   reg [31:0] test_case_fail = 0;

   reg test_passed = 1'b0;
   reg test_failed = 1'b0;
   integer test_count = 0;

   always @(posedge test_passed) begin
      $display("--------------------------------------------------------------------------------------------");
      $display("\n\n\033[1;32mTEST PASSED\033[0m  @ %d", $time);
      #100 $finish;

   end

   always @(posedge test_failed) begin
      $display("--------------------------------------------------------------------------------------------");
      $display("\n\033[1;31m***** TEST FAILED *****\033[0m @ %d\n", $time);
      #100 $finish;

   end

   //
   // Do not let a test bench just run forever.
   //
   initial begin
      #50000000;
      $display("TEST CASE TIMEOUT @ %d", $time);
      test_failed <= 1'b1;
   end

   /****************************************************************************
    TASK: all_tests_completed
    PARAMETERS:
    OPERATION:
        This task is called at the end of a test case to indicate it is done.
        If the correct number of test cases were executed we indicate this test
        has passed.  Otherwise we indicate failure.

    ***************************************************************************/
   task all_tests_completed;
      begin
         if (test_case_fail !== 0) begin
            test_failed <= 1;
         end else if (`NUMBER_OF_TESTS == test_count) begin
            test_passed <= 1;
         end else begin
            $display("INCORRECT NUMBER OF TESTS! Exp: %d  Ran: %d", `NUMBER_OF_TESTS, test_count);
            test_failed <= 1;
         end
      end
   endtask // if

   /****************************************************************************
    TASK: compare_values
    PARAMETERS:
        input [8*80:1] display_string;  -- Test to indicate which test this is
        input [31:0]   expected; -- Expected correct value
        input [31:0]   measured; -- Actual measured value

    OPERATION:
        This task is the one called from the test cases.  It checks for bad data (X)
        and compares the expected and measured values.  Sets the pass/fail flag
        and calls the display_results task.

    ***************************************************************************/
   task compare_values;
      input [8*80:1] display_string;
      input [31:0]   expected;
      input [31:0]   measured;

      begin

         if (|measured == 1'bX) begin
            display_results("Data is X", expected, measured);
            //`TEST_FAILED <= 1'b1;
         end else begin
            if (expected !== measured) begin
               test_case_fail <= test_case_fail + 1;
               //$display("EXP: 0x%h\tMeasure:0x%h", expected, measured);
               #1 display_results(display_string, expected, measured);
            end else begin
               #1 display_results(display_string, expected, measured);
            end
         end
      end
   endtask

   /****************************************************************************
    TASK: display_results
    PARAMETERS:
        input [8*80:1] display_string;  -- Test to indicate which test this is
        input [31:0]   expected; -- Expected correct value
        input [31:0]   measured; -- Actual measured value

    OPERATION:
        This task will display the table of tests with their time stamp,
        test number, string, expected, measured and results.

    ***************************************************************************/
   task display_results;
      input [8*80:1] display_string;
      input [31:0]   expected;
      input [31:0]   measured;

      reg [17*8-1:0]     pass_fail;

      begin
         if (test_case_fail) begin
            pass_fail = "\033[1;31mFAIL\033[0m";
         end else begin
            pass_fail = "\033[1;32mPASS\033[0m";
         end

         // left justify string
         while (display_string[8*35:8*35-7] == 8'h00)begin
            display_string = {display_string," "};
         end

         if (test_count == 0) begin
            $display("--------------------------------------------------------------------------------------------");
            $display("|TIME |Test| \tTest Case \t\t\t\t|Expected   |\tMeasured   | State |");
            $display("--------------------------------------------------------------------------------------------");
         end

         test_count <= test_count + 1;
         $display("|%4d |%4d|\t%0s \t|0x%8h |\t0x%8h |%s |", $time-1, test_count, display_string, expected, measured, pass_fail);
         if (((test_count %10) == 0) && test_count >0) begin
            $display("--------------------------------------------------------------------------------------------");
         end


      end

   endtask //


endmodule // test_tasks

AXI_Stream/master_rtl/axis_m.v
// Simple AXI-Stream Master
// Takes the data and sends it through the AXIS interface
// When send posedge happens, sends the data


`timescale 1us/1us

module axis_m ( input areset_n,
				input aclk,
				input [31:0] data,
				input send,

				input tready,
				output reg tvalid,
				output tlast,
				output reg [31:0] tdata,

				output reg finish
			);


/* -----\/----- EXCLUDED -----\/-----
reg [31:0] data_buf; // buffer to keep the send data from change
always @ (posedge send or negedge areset_n)
	if (~areset_n)
		data_buf <= 0;
	else
		data_buf <= data;
 -----/\----- EXCLUDED -----/\----- */

reg send_pulse_1d,send_pulse_2d;
// just delay the send signal
always @ (posedge aclk)
    if (~areset_n)
		{send_pulse_1d,send_pulse_2d } <= 2'b00;
	else
		{send_pulse_1d,send_pulse_2d } <= {send, send_pulse_1d};


// handshake happened between master and slave
wire handshake;
assign handshake  = tvalid & tready;

// tdata
always @ (posedge aclk)
    if (~areset_n)
        tdata <= 32'b0;
	else
		if (handshake)
			tdata <= 0;
		else if (send_pulse_1d)
				tdata <= data;
			else
				tdata <= tdata;

// tvalid
// as soon as the fifo becomes no empty the tvalid goes high
always @ (posedge aclk)
    if (~areset_n)
        tvalid <= 1'b0;
    else
		if (handshake)
			tvalid <= 1'b0;
		else
			if (send_pulse_1d )
				tvalid <= 1'b1;
			else
				tvalid <= tvalid;

// tlast
// same behavioral as tvalid
assign tlast = tvalid;

// finish
always @ (posedge aclk)
    if (~areset_n)
        finish <= 1'b0;
	else
		if (send_pulse_1d)
			finish <= 1'b0;
		else
			if (handshake)
				finish <= 1'b1;
			else
				finish <= 1'b0;


endmodule

AXI_Stream/master_rtl/tb_axis_m.v
//                              -*- Mode: Verilog -*-
// Filename        : tb_axis_m.v
// Description     : Testbench for AXI Streaming Master
// Author          : Philip Tracton
// Created On      : Sat Mar 23 12:42:27 2019
// Last Modified By: Philip Tracton
// Last Modified On: Sat Mar 23 12:42:27 2019
// Update Count    : 0
// Status          : Unknown, Use with caution!

`define TB tb_axis_m
`define NUMBER_OF_TESTS 2

`include "test_axi_include.v"


module tb_axis_m (/*AUTOARG*/ ) ;


   reg aclk;
   initial begin
      aclk = 0;
      forever begin
         #2 aclk = ~aclk;
      end
   end

   reg areset_n;
   initial begin
      areset_n = 0;
      repeat(5) @(posedge aclk);
      #1 areset_n = 1;
   end


   reg send;
   wire finish;

   reg  tready;
   wire tvalid, tlast;
   wire [31:0] tdata;
   reg [31:0]  data;


   axis_m inst_axis_m (.areset_n(areset_n),
                       .aclk(aclk),
					   .data(data),
					   .send(send),
					   .tready(tready),
                       .tvalid(tvalid),
                       .tlast(tlast),
                       .tdata(tdata),
					   .finish (finish)
					   );
   //
   // TASK: stream_data
   // This task will transfer 1 word into the AXI Streaming Master
   //
   task stream_data;
      input [31:0] sdata;
      begin

         // This starts asych
         send = 1;
         data = sdata;
         tready = 1;

         // synch clock
         @(posedge aclk);
         //send = 1;
         tready = 0;
         // hold clock
         @(posedge aclk);
         send = 0;
         tready = 1;
         data = $random;

         @(posedge tvalid);

         `TEST_COMPARE("STREAM DATA", sdata, tdata);
      end
   endtask

   //
   // Test Case:
   //
   initial begin
      send = 0;
      tready = 1;
      data = 0;

      // Wait for reset to release
      @(posedge areset_n);
      repeat(5) @(posedge aclk);
      #1 stream_data(32'haaaa_bbbb);
      #2 stream_data(32'hcccc_dddd);
      repeat(5) @(posedge aclk);
      `TEST_COMPLETE();
   end

   //
   // test_tasks is our generic set of tools for handling test cases
   //
   test_tasks test_tasks();

   //
   // dump to wveform viewer
   //
   dump dump();


endmodule // tb_axis_m

AXI_Stream/master_rtl/dump.vcd
$date
	Sat Mar 23 14:27:52 2019
$end
$version
	Icarus Verilog
$end
$timescale
	1us
$end
$scope module tb_axis_m $end
$var wire 1 ! tvalid $end
$var wire 1 " tlast $end
$var wire 32 # tdata [31:0] $end
$var wire 1 $ finish $end
$var reg 1 % aclk $end
$var reg 1 & areset_n $end
$var reg 32 ' data [31:0] $end
$var reg 1 ( send $end
$var reg 1 ) tready $end
$scope module dump $end
$upscope $end
$scope module inst_axis_m $end
$var wire 1 % aclk $end
$var wire 1 & areset_n $end
$var wire 32 * data [31:0] $end
$var wire 1 + handshake $end
$var wire 1 ( send $end
$var wire 1 " tlast $end
$var wire 1 ) tready $end
$var reg 1 $ finish $end
$var reg 1 , send_pulse_1d $end
$var reg 1 - send_pulse_2d $end
$var reg 32 . tdata [31:0] $end
$var reg 1 ! tvalid $end
$upscope $end
$scope module test_tasks $end
$var reg 32 / test_case_fail [31:0] $end
$var reg 1 0 test_failed $end
$var reg 1 1 test_passed $end
$var integer 32 2 test_count [31:0] $end
$scope task all_tests_completed $end
$upscope $end
$scope task compare_values $end
$var reg 640 3 display_string [640:1] $end
$var reg 32 4 expected [31:0] $end
$var reg 32 5 measured [31:0] $end
$upscope $end
$scope task display_results $end
$var reg 640 6 display_string [640:1] $end
$var reg 32 7 expected [31:0] $end
$var reg 32 8 measured [31:0] $end
$var reg 136 9 pass_fail [135:0] $end
$upscope $end
$upscope $end
$scope task stream_data $end
$var reg 32 : sdata [31:0] $end
$upscope $end
$upscope $end
$enddefinitions $end
#0
$dumpvars
bx :
bx 9
bx 8
bx 7
bx 6
bx 5
bx 4
bx 3
b0 2
01
00
b0 /
bx .
x-
x,
x+
b0 *
1)
0(
b0 '
0&
0%
x$
bx #
x"
x!
$end
#2
0+
0,
0-
b0 #
b0 .
0"
0!
0$
1%
#4
0%
#6
1%
#8
0%
#10
1%
#12
0%
#14
1%
#16
0%
#18
1%
#19
1&
#20
0%
#22
1%
#24
0%
#26
1%
#28
0%
#30
1%
#32
0%
#34
1%
#36
0%
#38
1%
#39
b10101010101010101011101110111011 '
b10101010101010101011101110111011 *
1(
b10101010101010101011101110111011 :
#40
0%
#42
1,
0)
1%
#44
0%
#46
b10101010101010101011101110111011 5
b10101010101010101011101110111011 4
b101001101010100010100100100010101000001010011010010000001000100010000010101010001000001 3
1+
1"
1!
b10101010101010101011101110111011 #
b10101010101010101011101110111011 .
1-
b10010000101010011010100100100 '
b10010000101010011010100100100 *
1)
0(
1%
#47
b1 2
b110110101101100110001001110110011001100110010011011010101000001000001010100110101001100011011010110110011000001101101 9
b10101010101010101011101110111011 8
b10101010101010101011101110111011 7
b101001101010100010100100100010101000001010011010010000001000100010000010101010001000001001000000010000000100000001000000010000000100000001000000010000000100000001000000010000000100000001000000010000000100000001000000010000000100000001000000010000000100000001000000010000000100000 6
#48
0%
#49
b11001100110011001101110111011101 '
b11001100110011001101110111011101 *
1(
b11001100110011001101110111011101 :
#50
b0 #
b0 .
0"
0!
0+
0)
1%
#52
0%
#54
b11001100110011001101110111011101 5
b11001100110011001101110111011101 4
1+
1"
1!
b11001100110011001101110111011101 #
b11001100110011001101110111011101 .
b11000000100010010101111010000001 '
b11000000100010010101111010000001 *
1)
0(
1%
#55
b10 2
b11001100110011001101110111011101 8
b11001100110011001101110111011101 7
b101001101010100010100100100010101000001010011010010000001000100010000010101010001000001001000000010000000100000001000000010000000100000001000000010000000100000001000000010000000100000001000000010000000100000001000000010000000100000001000000010000000100000001000000010000000100000 6
#56
0%
#58
0+
0,
b0 #
b0 .
0"
0!
1%
#60
0%
#62
0-
1%
#64
0%
#66
1%
#68
0%
#70
1%
#72
0%
#74
11
1%
